init_tikz/__init__.py
init_tikz/__main__.py
init_tikz/functions_tex.py
init_tikz/main.py
init_tikz-0.1.16.dist-info/METADATA
init_tikz-0.1.16.dist-info/WHEEL
init_tikz-0.1.16.dist-info/entry_points.txt
init_tikz-0.1.16.dist-info/RECORD
