Metadata-Version: 2.1
Name: init-tikz
Version: 0.1.16
Summary: Added qrcode.
Author: vaibhavblayer
Author-email: vaibhavblayer@gmail.com
Requires-Python: >=3.11,<4.0
Classifier: Programming Language :: Python :: 3
Classifier: Programming Language :: Python :: 3.11
